PyXAB/__init__.py
PyXAB/run_synthetic.py
PyXAB/algos/Algo.py
PyXAB/algos/DOO.py
PyXAB/algos/GPO.py
PyXAB/algos/HCT.py
PyXAB/algos/HOO.py
PyXAB/algos/PCT.py
PyXAB/algos/POO.py
PyXAB/algos/SOO.py
PyXAB/algos/SequOOL.py
PyXAB/algos/StoSOO.py
PyXAB/algos/StroquOOL.py
PyXAB/algos/VHCT.py
PyXAB/algos/VPCT.py
PyXAB/algos/VROOM.py
PyXAB/algos/Zooming.py
PyXAB/algos/__init__.py
PyXAB/partition/BinaryPartition.py
PyXAB/partition/DimensionBinaryPartition.py
PyXAB/partition/DimensionPartition.py
PyXAB/partition/KaryPartition.py
PyXAB/partition/Node.py
PyXAB/partition/Partition.py
PyXAB/partition/RandomBinaryPartition.py
PyXAB/partition/RandomKaryPartition.py
PyXAB/partition/__init__.py
PyXAB/partition/test_partition.py
PyXAB/synthetic_obj/Ackley.py
PyXAB/synthetic_obj/Cexample.py
PyXAB/synthetic_obj/DifficultFunc.py
PyXAB/synthetic_obj/DoubleSine.py
PyXAB/synthetic_obj/Garland.py
PyXAB/synthetic_obj/Himmelblau.py
PyXAB/synthetic_obj/Objective.py
PyXAB/synthetic_obj/Rastrigin.py
PyXAB/synthetic_obj/__init__.py
PyXAB/utils/__init__.py
PyXAB/utils/plot.py
PyXAB/utils/run_cumulative.py
PyXAB/utils/run_synthetic.py
PyXAB/utils/visualize_gif.py
PyXAB-0.3.0.dist-info/LICENSE
PyXAB-0.3.0.dist-info/METADATA
PyXAB-0.3.0.dist-info/WHEEL
PyXAB-0.3.0.dist-info/top_level.txt
PyXAB-0.3.0.dist-info/RECORD
