Metadata-Version: 2.1
Name: PyXAB
Version: 0.3.0
Summary: PyXAB - A Python Library for X-Armed Bandit and Online Blackbox Optimization Algorithms.
Home-page: https://github.com/WilliamLwj/PyXAB
Author: Wenjie Li, Haoze Li, Qifan Song, Jean Honorio
Author-email: lil3549@purdue.edu
License: MIT
Platform: UNKNOWN
Classifier: License :: OSI Approved :: MIT License
Classifier: Programming Language :: Python
Classifier: Programming Language :: Python :: 3
Classifier: Programming Language :: Python :: 3.6
Classifier: Programming Language :: Python :: Implementation :: CPython
Classifier: Programming Language :: Python :: Implementation :: PyPy
Requires-Python: >=3.6.0
Requires-Dist: numpy (>=1.20.3)
Requires-Dist: matplotlib
